rs4/__init__.py
rs4/annotations.py
rs4/argopt.py
rs4/asynchat.py
rs4/asyncore.py
rs4/attrdict.py
rs4/confparse.py
rs4/evbus.py
rs4/importer.py
rs4/logger.py
rs4/pathtool.py
rs4/termcolor.py
rs4/apis/__init__.py
rs4/apis/telegram.py
rs4/apis/aws/__init__.py
rs4/apis/aws/cloudwatch.py
rs4/apis/aws/cost_explorer.py
rs4/apis/aws/deploy.py
rs4/apis/aws/ec2.py
rs4/apis/aws/rds.py
rs4/apis/aws/s3.py
rs4/apis/aws/speech.py
rs4/apis/aws/stream_transcribe.py
rs4/apis/aws/transcribe.py
rs4/apis/aws/translate.py
rs4/apis/aws/ec2ops/__init__.py
rs4/apis/aws/ec2ops/autoscaler.py
rs4/apis/aws/ec2ops/elb.py
rs4/apis/aws/ec2ops/elbops3.py
rs4/apis/aws/ec2ops/iquery.py
rs4/apis/aws/ec2ops/metrics.py
rs4/apis/aws/ec2ops/ssh.py
rs4/apis/aws/ec2ops/ssh3.py
rs4/apis/etri/__init__.py
rs4/apis/etri/asr.py
rs4/apis/etri/wikiqa.py
rs4/apis/gitlab/__init__.py
rs4/apis/google/__init__.py
rs4/apis/google/requirements.txt
rs4/apis/google/speech.py
rs4/apis/google/assistant/__init__.py
rs4/apis/google/assistant/assistant.py
rs4/apis/google/assistant/device_register.py
rs4/apis/google/assistant/modulator.py
rs4/apis/google/assistant/requirements.txt
rs4/apis/google/assistant/sources.py
rs4/apis/google/assistant/grpc/__init__.py
rs4/apis/google/assistant/grpc/assistant_helpers.py
rs4/apis/google/assistant/grpc/audio_helpers.py
rs4/apis/google/assistant/grpc/audiofileinput.py
rs4/apis/google/assistant/grpc/browser_helpers.py
rs4/apis/google/assistant/grpc/device_helpers.py
rs4/apis/google/assistant/grpc/devicetool.py
rs4/apis/google/assistant/grpc/pushtotalk.py
rs4/apis/google/assistant/grpc/textinput.py
rs4/apis/houndify/__init__.py
rs4/apis/houndify/houndify.py
rs4/apis/houndify/sample_stdin.py
rs4/apis/houndify/sample_text.py
rs4/apis/houndify/sample_wave.py
rs4/apis/mycroft/__init__.py
rs4/apis/mycroft/precise/__init__.py
rs4/apis/mycroft/precise/detector.py
rs4/apis/mycroft/precise/engine.py
rs4/apis/mycroft/precise/listener.py
rs4/apis/shared/__init__.py
rs4/apis/shared/ssml.py
rs4-0.3.32.dist-info/licenses/LICENSE
rs4-0.3.32.dist-info/METADATA
rs4-0.3.32.dist-info/WHEEL
rs4-0.3.32.dist-info/top_level.txt
rs4-0.3.32.dist-info/RECORD
