Metadata-Version: 2.4
Name: rs4
Version: 0.3.32
Summary: Utility Pack
Home-page: https://gitlab.com/skitai/rs4
Download-URL: https://pypi.python.org/pypi/rs4
Author: Hans Roh
Author-email: hansroh@gmail.com
License: MIT
Platform: posix
Platform: nt
Classifier: Development Status :: 4 - Beta
Classifier: Topic :: Utilities
Classifier: Environment :: Console
Classifier: Topic :: Software Development :: Libraries :: Python Modules
Classifier: Intended Audience :: Developers
Classifier: Programming Language :: Python
Classifier: Programming Language :: Python :: 3
License-File: LICENSE
Requires-Dist: psutil
Requires-Dist: requests
Requires-Dist: colorama
Requires-Dist: tqdm
Requires-Dist: setproctitle
Requires-Dist: setproctitle
Dynamic: author
Dynamic: author-email
Dynamic: classifier
Dynamic: description
Dynamic: download-url
Dynamic: home-page
Dynamic: license
Dynamic: license-file
Dynamic: platform
Dynamic: requires-dist
Dynamic: summary
